pyratings/__init__.py
pyratings/aggregate.py
pyratings/clean.py
pyratings/consolidate.py
pyratings/get_ratings.py
pyratings/get_scores.py
pyratings/get_warf.py
pyratings/resources/__init__.py
pyratings/resources/Ratings.db
pyratings/utils.py
pyratings/warf.py
pyratings-0.6.1.dist-info/WHEEL
pyratings-0.6.1.dist-info/METADATA
pyratings-0.6.1.dist-info/licenses/LICENSE
pyratings-0.6.1.dist-info/RECORD
