Metadata-Version: 2.1
Name: pyratings
Version: 0.6.1
Summary: Working with credit ratings, professionally and efficiently
Keywords: ratings,credit ratings,rating scores
Author-email: HSBC <opensource@hsbc.com>
Requires-Python: >=3.9
Classifier: Development Status :: 4 - Beta
Classifier: License :: OSI Approved :: Apache Software License
Classifier: Natural Language :: English
Classifier: Operating System :: OS Independent
Classifier: Programming Language :: Python :: 3.10
Classifier: Programming Language :: Python :: 3.11
Classifier: Programming Language :: Python :: 3.9
Classifier: Topic :: Office/Business :: Financial
Classifier: Topic :: Office/Business :: Financial :: Accounting
Classifier: Topic :: Office/Business :: Financial :: Investment
Requires-Dist: numpy>=1.20.0
Requires-Dist: pandas>=1.0.0
Project-URL: BugTracker, https://github.com/hsbc/pyratings/issues?q=label%3Abug+
Project-URL: Changelog, https://github.com/hsbc/pyratings/blob/main/CHANGELOG.md
Project-URL: Documentation, https://hsbc.github.io/pyratings/
Project-URL: Homepage, https://hsbc.github.io/pyratings/
Project-URL: Repository, https://github.com/hsbc/pyratings
